LICENSE
README.md
setup.py
other/__init__.py
other/dw_hg.py
pycrawlers/__init__.py
pycrawlers.egg-info/PKG-INFO
pycrawlers.egg-info/SOURCES.txt
pycrawlers.egg-info/dependency_links.txt
pycrawlers.egg-info/requires.txt
pycrawlers.egg-info/top_level.txt
pycrawlers/common/__init__.py
pycrawlers/common/default_data.py
pycrawlers/common/tools.py
pycrawlers/huggingfaces/__init__.py
pycrawlers/huggingfaces/download.py
pycrawlers/websites/__init__.py
pycrawlers/websites/get_web_page.py
pycrawlers/websites/get_web_page_id.py
pycrawlers/websites/get_websites.py
pycrawlers/websites/url_filters.py