Metadata-Version: 2.1
Name: pycrawlers
Version: 1.1.1
Summary: A collection of Crawlers
Home-page: https://gitee.com/maxbanana
Author: hongbo liu
Author-email: 782027465@qq.com
License: Apache
Platform: UNKNOWN
Classifier: Programming Language :: Python :: 3
Classifier: License :: OSI Approved :: Apache Software License
Classifier: Operating System :: OS Independent
Requires-Python: >=3.6
License-File: LICENSE
